position_finder/__init__.py
position_finder/data.py
position_finder/gui.py
position_finder/position_finder.py
position_finder/servo_control.py
ai_robot_position_finder-0.1.1.dist-info/METADATA
ai_robot_position_finder-0.1.1.dist-info/WHEEL
ai_robot_position_finder-0.1.1.dist-info/entry_points.txt
ai_robot_position_finder-0.1.1.dist-info/top_level.txt
ai_robot_position_finder-0.1.1.dist-info/RECORD
