Metadata-Version: 2.4
Name: ai-robot-position-finder
Version: 0.1.1
Summary: Python app to control the 16 Servo positions
Home-page: 
Author: Arun CS
Author-email: aruncs31s@proton.com
Requires-Dist: requests
Requires-Dist: click
Requires-Dist: ai-robot-position-scraper
Dynamic: author
Dynamic: author-email
Dynamic: description
Dynamic: description-content-type
Dynamic: requires-dist
Dynamic: summary
